Metadata-Version: 2.1
Name: Splinicode
Version: 14.0.3
Summary: Splitting unicode text into graphemes (Support unicode 14.0.0)
Home-page: UNKNOWN
Author: LordObit
Author-email: lordorbitus@gmail.com
License: UNKNOWN
Platform: MacOS
Platform: Windows
Platform: Linux
